[
    {
        "content": "<p>In <a href=\"https://rust-analyzer.github.io/book/non_cargo_based_projects.html?highlight=non-cargo#non-cargo-based-projects\">non-cargo based projects</a>, calls to <code>cargo check</code> are disabled, because it doesn't exist. Is there any alternative command in the Makefile that compiles only the rust code? given that the <code>rust/bindings</code> have been generated.</p>",
        "id": 537732386,
        "sender_full_name": "ManeraKai",
        "timestamp": 1757011794
    },
    {
        "content": "<p>No (at the moment at least) -- what do you need it for?</p>",
        "id": 537733812,
        "sender_full_name": "Miguel Ojeda",
        "timestamp": 1757012434
    },
    {
        "content": "<p>To not build the whole kernel every time to see if the rustc will give me any errors, after changing a single file.</p>",
        "id": 537735370,
        "sender_full_name": "ManeraKai",
        "timestamp": 1757013081
    },
    {
        "content": "<p>A build after modifying a file should not rebuild the whole kernel.</p>",
        "id": 537735782,
        "sender_full_name": "Miguel Ojeda",
        "timestamp": 1757013276
    },
    {
        "content": "<p>If it does, then it sounds like you are cleaning your build directory or similar.</p>",
        "id": 537735914,
        "sender_full_name": "Miguel Ojeda",
        "timestamp": 1757013337
    },
    {
        "content": "<p>(We may have a bug etc. too, of course, but the point is that it should not be happening that your whole kernel gets rebuilt)</p>",
        "id": 537736023,
        "sender_full_name": "Miguel Ojeda",
        "timestamp": 1757013398
    },
    {
        "content": "<p>having a target to just check the rust code (so just see if the compiler would emit any typing-errors) would be very useful to me</p>",
        "id": 538908054,
        "sender_full_name": "Benno Lossin",
        "timestamp": 1757609980
    },
    {
        "content": "<p>should be not so hard to support that, I can have a look into that today</p>",
        "id": 538984181,
        "sender_full_name": "Onur Özkan",
        "timestamp": 1757654278
    },
    {
        "content": "<p>would be extremely great if it didn't have to compile any (or almost no) C code, I could then use it in my rust-compile tests I do for pin-init</p>",
        "id": 538996854,
        "sender_full_name": "Benno Lossin",
        "timestamp": 1757661263
    },
    {
        "content": "<p>Yeah that's what I am planning to do</p>",
        "id": 539000009,
        "sender_full_name": "Onur Özkan",
        "timestamp": 1757662502
    },
    {
        "content": "<p>Almost there:</p>\n<div class=\"codehilite\" data-code-language=\"Bash\"><pre><span></span><code>~/devspace/onur-ozkan/linux<span class=\"w\"> </span>$<span class=\"w\"> </span><span class=\"nb\">time</span><span class=\"w\"> </span>make<span class=\"w\"> </span><span class=\"nv\">LLVM</span><span class=\"o\">=</span><span class=\"m\">1</span><span class=\"w\"> </span>-j<span class=\"w\"> </span><span class=\"k\">$(</span>nproc<span class=\"k\">)</span><span class=\"w\"> </span>rustcheck\n<span class=\"w\">  </span>RUSTC<span class=\"w\"> </span>CHECK<span class=\"w\"> </span>rust/macros/lib.rs\n<span class=\"w\">  </span>RUSTC<span class=\"w\"> </span>CHECK<span class=\"w\"> </span>rust/pin-init/internal/src/lib.rs\n<span class=\"w\">  </span>RUSTC<span class=\"w\"> </span>CHECK<span class=\"w\"> </span>rust/build_error.rs\n<span class=\"w\">  </span>RUSTC<span class=\"w\"> </span>CHECK<span class=\"w\"> </span>rust/ffi.rs\n<span class=\"w\">  </span>RUSTC<span class=\"w\"> </span>CHECK<span class=\"w\"> </span>rust/bindings/lib.rs\n<span class=\"w\">  </span>RUSTC<span class=\"w\"> </span>CHECK<span class=\"w\"> </span>rust/uapi/lib.rs\n<span class=\"w\">  </span>RUSTC<span class=\"w\"> </span>CHECK<span class=\"w\"> </span>rust/pin-init/src/lib.rs\n<span class=\"w\">  </span>RUSTC<span class=\"w\"> </span>CHECK<span class=\"w\"> </span>rust/kernel/lib.rs\nmake<span class=\"w\"> </span><span class=\"nv\">LLVM</span><span class=\"o\">=</span><span class=\"m\">1</span><span class=\"w\"> </span>-j<span class=\"w\"> </span><span class=\"k\">$(</span>nproc<span class=\"k\">)</span><span class=\"w\"> </span>rustcheck<span class=\"w\">  </span><span class=\"m\">5</span>.04s<span class=\"w\"> </span>user<span class=\"w\"> </span><span class=\"m\">1</span>.16s<span class=\"w\"> </span>system<span class=\"w\"> </span><span class=\"m\">169</span>%<span class=\"w\"> </span>cpu<span class=\"w\"> </span><span class=\"m\">3</span>.654<span class=\"w\"> </span>total\n~/devspace/onur-ozkan/linux<span class=\"w\"> </span>$\n</code></pre></div>\n<p>In practice, it does the job of \"checking the rust sources without actually building anything and touching any C code\" but there are some issues I still need to fix. First, current change in the rust/Makefile is extremely verbose, I need to rework that part. Second, it doesn't handle bindgen, so bindgen files need to be created before running the check (which means it doesn't work on a fresh checkout), I will work on that too. I am off for today (going to watch Eurobasket :) ). I will work on it over the weekend or early next week.</p>",
        "id": 539052146,
        "sender_full_name": "Onur Özkan",
        "timestamp": 1757680034
    },
    {
        "content": "<p><span class=\"user-mention silent\" data-user-id=\"928507\">Onur Özkan</span> <a href=\"#narrow/channel/288089-General/topic/Alternative.20to.20.60cargo.20check.60/near/538984181\">said</a>:</p>\n<blockquote>\n<p>should be not so hard to support that, I can have a look into that today</p>\n</blockquote>\n<p>I was quite wrong there xd</p>",
        "id": 539052202,
        "sender_full_name": "Onur Özkan",
        "timestamp": 1757680054
    },
    {
        "content": "<p>Is it fast?</p>",
        "id": 539053147,
        "sender_full_name": "Andreas Hindborg",
        "timestamp": 1757680346
    },
    {
        "content": "<p>Oh, you have numbers right there.</p>",
        "id": 539053256,
        "sender_full_name": "Andreas Hindborg",
        "timestamp": 1757680377
    },
    {
        "content": "<p>Can you compare it to <code>make rust/</code> ?</p>",
        "id": 539053343,
        "sender_full_name": "Andreas Hindborg",
        "timestamp": 1757680403
    },
    {
        "content": "<p>Yeah it is fast compare to <code>make LLVM=1 -j $(nproc) rust/</code>:</p>\n<div class=\"codehilite\" data-code-language=\"Bash\"><pre><span></span><code>make<span class=\"w\"> </span><span class=\"nv\">LLVM</span><span class=\"o\">=</span><span class=\"m\">1</span><span class=\"w\"> </span>-j<span class=\"w\"> </span><span class=\"k\">$(</span>nproc<span class=\"k\">)</span><span class=\"w\"> </span>rust/<span class=\"w\">  </span><span class=\"m\">28</span>.07s<span class=\"w\"> </span>user<span class=\"w\"> </span><span class=\"m\">4</span>.07s<span class=\"w\"> </span>system<span class=\"w\"> </span><span class=\"m\">226</span>%<span class=\"w\"> </span>cpu<span class=\"w\"> </span><span class=\"m\">14</span>.217<span class=\"w\"> </span>total\n</code></pre></div>",
        "id": 539054412,
        "sender_full_name": "Onur Özkan",
        "timestamp": 1757680657
    },
    {
        "content": "<p>It's also not only about being faster, with check-only builds you can easily check for cross targets</p>",
        "id": 539054695,
        "sender_full_name": "Onur Özkan",
        "timestamp": 1757680735
    },
    {
        "content": "<p>fwiw my cpu is Intel Core Ultra 7 165U @ 14x 4.9GHz</p>",
        "id": 539055009,
        "sender_full_name": "Onur Özkan",
        "timestamp": 1757680822
    },
    {
        "content": "<p>Very cool!!!</p>",
        "id": 539103602,
        "sender_full_name": "Benno Lossin",
        "timestamp": 1757692262
    },
    {
        "content": "<p>Very cool. It looks like it is actually fast enough to run async on file save.</p>",
        "id": 539258693,
        "sender_full_name": "Andreas Hindborg",
        "timestamp": 1757757191
    },
    {
        "content": "<p><span class=\"user-mention\" data-user-id=\"554954\">@Matthew Maurer</span> here + <a href=\"https://lore.kernel.org/r/20250915115311.3025-1-work@onurozkan.dev\">https://lore.kernel.org/r/20250915115311.3025-1-work@onurozkan.dev</a></p>",
        "id": 540201739,
        "sender_full_name": "Andreas Hindborg",
        "timestamp": 1758192433
    },
    {
        "content": "<p>The patched was acked by Nicolas <a href=\"https://lore.kernel.org/all/aOlW3RFO9sm6IsIB@levanger/\">here</a>, any idea when it can be landed? It would be very useful for me when I am working on a laptop with limited resources.</p>",
        "id": 547433782,
        "sender_full_name": "Onur Özkan",
        "timestamp": 1761640227
    },
    {
        "content": "<p>As I said in v1, I am not planning to land it, sorry.</p>",
        "id": 547445674,
        "sender_full_name": "Miguel Ojeda",
        "timestamp": 1761644058
    },
    {
        "content": "<p><span class=\"user-mention silent\" data-user-id=\"411477\">Miguel Ojeda</span> <a href=\"#narrow/channel/288089-General/topic/Alternative.20to.20.60cargo.20check.60/near/547445674\">said</a>:</p>\n<blockquote>\n<p>As I said in v1, I am not planning to land it, sorry.</p>\n</blockquote>\n<p>Is it due to complexity (I can understand that, it's kind a duplicating a lot of things)? I would be happy to make it cleaner and simpler if that's the case. It would be really useful for me when I am working remotely on a low resource laptop (and I also see that there are other devs interested on this).</p>",
        "id": 569837001,
        "sender_full_name": "Onur Özkan",
        "timestamp": 1769231432
    },
    {
        "content": "<p>The build system is being reworked by Miguel and new feature would complicate that</p>",
        "id": 569865704,
        "sender_full_name": "Gary Guo",
        "timestamp": 1769260094
    },
    {
        "content": "<p>I see. I guess I will wait that and then implement check build on that</p>",
        "id": 569870199,
        "sender_full_name": "Onur Özkan",
        "timestamp": 1769263648
    }
]