[
    {
        "content": "<p>I'm collecting the list of pointers that we are using for some field projection work, am I missing any that are currently in-tree?</p>\n<ul>\n<li><code>KBox&lt;T&gt;</code></li>\n<li><code>KArc&lt;T&gt;</code></li>\n<li><code>UniqueKArc&lt;T&gt;</code></li>\n<li><code>ListArc&lt;T&gt;</code></li>\n<li><code>ARef&lt;T&gt;</code></li>\n<li><code>UserPtr</code></li>\n<li><code>IoMem</code></li>\n<li><code>&amp;Mmio</code></li>\n<li><code>CoherentBox&lt;T&gt;</code></li>\n<li><code>Coherent&lt;T&gt;</code></li>\n</ul>",
        "id": 592207525,
        "sender_full_name": "Benno Lossin",
        "timestamp": 1777610167
    },
    {
        "content": "<p>Are there any other interesting pointers that we have on-list or in the works?</p>",
        "id": 592207532,
        "sender_full_name": "Benno Lossin",
        "timestamp": 1777610174
    },
    {
        "content": "<p>I remember that we want to have the following pointers:</p>\n<ul>\n<li><code>AtomicPtr&lt;T&gt;</code></li>\n<li><code>VolatilePtr&lt;T&gt;</code> (or is that coherent or iomem from above?)</li>\n<li><code>Rcu</code> + <code>Mutex</code> (i.e. projecting from <code>&amp;Mutex&lt;Struct&gt;</code> to <code>&amp;Rcu&lt;Field&gt;</code> where <code>Struct.field: Rcu&lt;Field&gt;</code>)</li>\n</ul>\n<p>Am I forgetting any?</p>",
        "id": 592207873,
        "sender_full_name": "Benno Lossin",
        "timestamp": 1777610301
    },
    {
        "content": "<p>We have <code>Owned</code> <a href=\"https://lore.kernel.org/rust-for-linux/20260220-unique-ref-v15-0-893ed86b06cc@kernel.org/\">on list</a>, not sure if that is interesting for your work?</p>",
        "id": 592236848,
        "sender_full_name": "Andreas Hindborg",
        "timestamp": 1777624236
    },
    {
        "content": "<p>oh yeah that would also be improved with field projections</p>",
        "id": 592240368,
        "sender_full_name": "Benno Lossin",
        "timestamp": 1777626013
    },
    {
        "content": "<p>(maybe not substantially, but it should be on the list :)</p>",
        "id": 592240420,
        "sender_full_name": "Benno Lossin",
        "timestamp": 1777626034
    }
]