[
    {
        "content": "<p>I'd like to know if there are existing kernel modules which are already re-written in Rust? I want to learn to build kernel modules in Rust, but I have only \"hello-world\" examples.</p>\n<p>Is it possible to re-write, for example, a project like <code>ovpn-dco</code> to Rust currently?</p>",
        "id": 454795949,
        "sender_full_name": "Nikolai Shv",
        "timestamp": 1722250790
    },
    {
        "content": "<p>There are various projects listed below \"users\" in the sidebar at <a href=\"https://rust-for-linux.com/\">https://rust-for-linux.com/</a></p>",
        "id": 454802562,
        "sender_full_name": "Alice Ryhl",
        "timestamp": 1722252380
    },
    {
        "content": "<p><span class=\"user-mention silent\" data-user-id=\"740136\">Nikolai Shv</span> has marked this topic as resolved.</p>",
        "id": 455372667,
        "sender_full_name": "Notification Bot",
        "timestamp": 1722431607
    },
    {
        "content": "<p><span class=\"user-mention silent\" data-user-id=\"740136\">Nikolai Shv</span> has marked this topic as unresolved.</p>",
        "id": 455582248,
        "sender_full_name": "Notification Bot",
        "timestamp": 1722499861
    }
]