[
    {
        "content": "<p>Greetings,</p>\n<p>I've been playing around with Rust in the kernel for a few days now and I have a question:</p>\n<p>How am I supposed to load kernel modules? Is this supported yet? I've gone trough <code>rust/module_param.rs</code> but don't really have an idea on how to use it.</p>\n<p>I've used the <code>rust-out-of-tree</code> repo as a guide so far. </p>\n<p>I am new to Rust, and I really liked the idea of being able to write kernel modules in a language that isn't C.</p>\n<p>Thanks in advance!</p>",
        "id": 565886510,
        "sender_full_name": "Marko",
        "timestamp": 1767178938
    },
    {
        "content": "<p><span class=\"user-mention silent\" data-user-id=\"1009962\">Marko</span> <a href=\"#narrow/channel/291565-Help/topic/Loading.20kernel.20module.20params/near/565886510\">said</a>:</p>\n<blockquote>\n<p>How am I supposed to load kernel modules?</p>\n</blockquote>\n<p>Are you trying to just load a Rust kernel module? Or are you trying to use module params?</p>",
        "id": 565886862,
        "sender_full_name": "Alice Ryhl",
        "timestamp": 1767179289
    },
    {
        "content": "<p>Whoops, I meant <strong>load</strong> kernel module params within my Rust module.</p>\n<p>I have successfully compiled and loaded the rust out of tree example.</p>",
        "id": 565887380,
        "sender_full_name": "Marko",
        "timestamp": 1767179785
    },
    {
        "content": "<p>Essentially I am looking for a Rust reference for C's declaration of module params <code>module_param</code> fn.</p>",
        "id": 565887642,
        "sender_full_name": "Marko",
        "timestamp": 1767179963
    },
    {
        "content": "<p>The way to <em>load</em> a kernel module param is the same for C module params:</p>\n<div class=\"codehilite\" data-code-language=\"Bash\"><pre><span></span><code>sudo<span class=\"w\"> </span>modprobe<span class=\"w\"> </span>&lt;module_name&gt;<span class=\"w\"> </span>&lt;parameter_name&gt;<span class=\"o\">=</span>&lt;value&gt;\n</code></pre></div>",
        "id": 565887774,
        "sender_full_name": "Alice Ryhl",
        "timestamp": 1767180077
    },
    {
        "content": "<p>as for how to declare them</p>",
        "id": 565887810,
        "sender_full_name": "Alice Ryhl",
        "timestamp": 1767180110
    },
    {
        "content": "<p>there is some sample code in <code>samples/rust/rust_minimal.rs</code></p>",
        "id": 565887899,
        "sender_full_name": "Alice Ryhl",
        "timestamp": 1767180205
    },
    {
        "content": "<p><span class=\"user-mention silent\" data-user-id=\"519727\">Alice Ryhl</span> <a href=\"#narrow/channel/291565-Help/topic/Loading.20kernel.20module.20params/near/565887899\">said</a>:</p>\n<blockquote>\n<p>there is some sample code in <code>samples/rust/rust_minimal.rs</code></p>\n</blockquote>\n<p>Interesting, thanks! I believe this is what I was looking for.</p>",
        "id": 565888221,
        "sender_full_name": "Marko",
        "timestamp": 1767180477
    }
]