[
    {
        "content": "<p>When i try to \"make menuconfig\" but can`t find \"Rust support\" under \"General Setup\" with all \"depends on\" true  ? Is there something worng with my operation?</p>",
        "id": 321686475,
        "sender_full_name": "Caozhi",
        "timestamp": 1673889086
    },
    {
        "content": "<p>Have you tried \"make rustavailable\" first?</p>",
        "id": 321696097,
        "sender_full_name": "Boqun Feng",
        "timestamp": 1673892987
    },
    {
        "content": "<p>yes, and  i got a return \"Rust is available!\"</p>",
        "id": 321786146,
        "sender_full_name": "Caozhi",
        "timestamp": 1673947654
    },
    {
        "content": "<p>Please search for <code>RUST</code> in <code>menuconfig</code> and copy-paste the <code>Depends on: </code> line.</p>",
        "id": 321811672,
        "sender_full_name": "Miguel Ojeda",
        "timestamp": 1673956190
    },
    {
        "content": "<p>Prompt: Rust support                                                                                                                             <br>\n Depends on: HAVE_RUST [=y] &amp;&amp; RUST_IS_AVAILABLE [=y] &amp;&amp; !MODVERSIONS [=y] &amp;&amp; !GCC_PLUGINS [=y] &amp;&amp; !RANDSTRUCT [=y] &amp;&amp; !DEBUG_INFO_BTF [=y]</p>",
        "id": 321848117,
        "sender_full_name": "Caozhi",
        "timestamp": 1673966969
    },
    {
        "content": "<p>You need to disable <code>MODVERSIONS</code> etc. (notice the condition for some of those has a <code>!</code>)</p>",
        "id": 321854721,
        "sender_full_name": "Miguel Ojeda",
        "timestamp": 1673968588
    },
    {
        "content": "<p>oooooooooooh!!!!  I successed! Thank you so much! I think \"[=y]\" menas true in the expression included \"!\". you really help me a lot!!!</p>",
        "id": 321860741,
        "sender_full_name": "Caozhi",
        "timestamp": 1673970123
    },
    {
        "content": "<p>You're welcome!</p>",
        "id": 321863632,
        "sender_full_name": "Miguel Ojeda",
        "timestamp": 1673970853
    },
    {
        "content": "<p>I also struggled with this.  Created a PR here to clarify in the docs: <a href=\"https://github.com/Rust-for-Linux/linux/pull/955/files\">https://github.com/Rust-for-Linux/linux/pull/955/files</a></p>\n<p>I didn't understand how to find the <code>Depends on:</code> block referred to above. Does this show in the UI somewhere when one runs <code>make menuconfig</code>?</p>",
        "id": 324120234,
        "sender_full_name": "Matt Gilbride",
        "timestamp": 1674842483
    },
    {
        "content": "<p>I replied there -- yeah, please give a try to the \"Search\" functionality via the <code>/</code> key/button.</p>",
        "id": 324121104,
        "sender_full_name": "Miguel Ojeda",
        "timestamp": 1674842708
    },
    {
        "content": "<p>It will show the formula and what is currently met or not for all found symbols.</p>",
        "id": 324121172,
        "sender_full_name": "Miguel Ojeda",
        "timestamp": 1674842725
    },
    {
        "content": "<p>Ah - this makes sense.  Thanks!  Responded on the PR as well</p>",
        "id": 324124948,
        "sender_full_name": "Matt Gilbride",
        "timestamp": 1674843837
    },
    {
        "content": "<p>My pleasure!</p>",
        "id": 324125141,
        "sender_full_name": "Miguel Ojeda",
        "timestamp": 1674843891
    }
]